checker21/__init__.py
checker21/application.py
checker21/checkers/__init__.py
checker21/checkers/basic.py
checker21/checkers/norminette.py
checker21/conf/__init__.py
checker21/conf/default_settings.py
checker21/conf/environment.py
checker21/conf/exceptions.py
checker21/core/__init__.py
checker21/core/checker.py
checker21/core/project.py
checker21/core/subject.py
checker21/management/__init__.py
checker21/management/base.py
checker21/management/errors.py
checker21/management/commands/__init__.py
checker21/management/commands/help.py
checker21/management/commands/list.py
checker21/management/commands/norm.py
checker21/management/commands/norminette.py
checker21/management/commands/shell.py
checker21/management/commands/startproject.py
checker21/management/commands/test.py
checker21/management/commands/version.py
checker21/norminette/__init__.py
checker21/norminette/ast.py
checker21/norminette/context.py
checker21/norminette/fix_machine.py
checker21/norminette/registry.py
checker21/norminette/rules/__init__.py
checker21/norminette/rules/fix_assignation_indent.py
checker21/norminette/rules/fix_block_start.py
checker21/norminette/rules/fix_control_statement.py
checker21/norminette/rules/fix_empty_line.py
checker21/norminette/rules/fix_expression_statement.py
checker21/norminette/rules/fix_func_declaration.py
checker21/norminette/rules/fix_line_indent.py
checker21/norminette/rules/fix_many_instructions.py
checker21/norminette/rules/fix_nest_line_indent.py
checker21/norminette/rules/fix_newline_indent.py
checker21/norminette/rules/fix_operators_spacing.py
checker21/norminette/rules/fix_preprocessor_indent.py
checker21/norminette/rules/fix_prototype_indent.py
checker21/norminette/rules/fix_spacing.py
checker21/norminette/rules/fix_utype_declaration.py
checker21/norminette/rules/fix_variable_indent.py
checker21/projects/__init__.py
checker21/projects/get_next_line/__init__.py
checker21/projects/get_next_line/checkers.py
checker21/projects/get_next_line/project.py
checker21-0.2.5a0.dist-info/METADATA
checker21-0.2.5a0.dist-info/WHEEL
checker21-0.2.5a0.dist-info/entry_points.txt
checker21-0.2.5a0.dist-info/top_level.txt
checker21-0.2.5a0.dist-info/RECORD
